atom3/__init__.py
atom3/case.py
atom3/complex.py
atom3/conservation.py
atom3/database.py
atom3/main.py
atom3/neighbors.py
atom3/pair.py
atom3/parse.py
atom3/sequence.py
atom3/structure.py
atom3_py3-0.1.4.9.dist-info/LICENSE
atom3_py3-0.1.4.9.dist-info/METADATA
atom3_py3-0.1.4.9.dist-info/WHEEL
atom3_py3-0.1.4.9.dist-info/entry_points.txt
atom3_py3-0.1.4.9.dist-info/top_level.txt
atom3_py3-0.1.4.9.dist-info/RECORD
