Metadata-Version: 2.1
Name: atom3-py3
Version: 0.1.4.9
Summary: 3D Atomic Data Processing (Python 3 version)
Home-page: https://github.com/amorehead/atom3
Author: Raphael Townshend
Author-email: UNKNOWN
License: MIT
Platform: UNKNOWN
Requires-Dist: biopython
Requires-Dist: click
Requires-Dist: easy-parallel-py3
Requires-Dist: h5py
Requires-Dist: pandas
Requires-Dist: scipy
